pyhelm3/__init__.py
pyhelm3/client.py
pyhelm3/command.py
pyhelm3/errors.py
pyhelm3/models.py
pyhelm3-0.4.0.dist-info/LICENSE
pyhelm3-0.4.0.dist-info/METADATA
pyhelm3-0.4.0.dist-info/WHEEL
pyhelm3-0.4.0.dist-info/top_level.txt
pyhelm3-0.4.0.dist-info/RECORD
