Metadata-Version: 2.1
Name: pyhelm3
Version: 0.4.0
Summary: Python library for managing Helm releases using Helm 3.
Home-page: https://github.com/azimuth-cloud/pyhelm3
Author: Matt Pryor
Author-email: matt@stackhpc.com
License-File: LICENSE
Requires-Dist: pydantic
Requires-Dist: pyyaml
